[
  {
    "id": 1782588434305,
    "title": "Singapore's Rising Stars: How New Project Launches Are Revolutionizing the Real Estate Scene",
    "category": "Market Update",
    "excerpt": "Discover how new project launches are driving momentum in Singapore's real estate market, and what this means for investors and enthusiasts alike. Get the inside scoop on the latest trends and opportunities.",
    "image": "https://images.unsplash.com/photo-1545324418-cc1a3fa10c00?auto=format&fit=crop&w=1200&q=80",
    "content": "\n## Introduction to Singapore's Thriving Real Estate Market\nSingapore's real estate market is experiencing a surge in momentum, driven by a wave of new project launches that are redefining the landscape. With increased demand for modern executive condominiums, investors and enthusiasts are taking notice of the opportunities that this thriving market has to offer.\n\n## New Project Launches: The Catalyst for Growth\nNew project launches are the primary driver behind Singapore's real estate momentum. These launches bring with them a plethora of benefits, including innovative designs, cutting-edge amenities, and unparalleled quality. As a result, investors are flocking to these new projects, eager to capitalize on the potential for long-term growth and returns.\n\n### The Rise of Modern Executive Condominiums\nModern executive condominiums are experiencing a significant surge in demand, as buyers seek out luxurious living spaces that offer the perfect blend of comfort, convenience, and style. These condominiums boast sleek designs, top-notch amenities, and prime locations, making them an attractive option for discerning investors and homeowners.\n\n## What This Means for Real Estate Enthusiasts and Investors\nFor real estate enthusiasts and investors, the current market trends present a wealth of opportunities. With new project launches and increased demand for modern executive condominiums, there has never been a better time to invest in Singapore's real estate market. Whether you're a seasoned investor or just starting out, it's essential to stay informed about the latest trends and developments to make the most of your investment portfolio.\n\n## Staying Ahead of the Curve\nTo stay ahead of the curve, it's crucial to work with a reputable and experienced real estate partner who can provide valuable insights and guidance. At Real Estate Enthusiast, we are committed to helping our clients navigate the complex world of real estate, providing expert advice and tailored solutions to meet their unique needs and goals.\n\n## Conclusion\nSingapore's real estate market is on the rise, driven by new project launches and increased demand for modern executive condominiums. As a real estate enthusiast or investor, it's essential to stay informed about the latest trends and developments to capitalize on the opportunities that this thriving market has to offer. With the right partner by your side, you can unlock the full potential of your investment portfolio and achieve your long-term goals.",
    "date": "28 June 2026"
  }
]